meta_optimizer/__init__.py
meta_optimizer/__main__.py
meta_optimizer/cli.py
meta_optimizer/benchmark/__init__.py
meta_optimizer/benchmark/test_functions.py
meta_optimizer/drift/__init__.py
meta_optimizer/drift/detector.py
meta_optimizer/drift_detection/__init__.py
meta_optimizer/drift_detection/drift_detector.py
meta_optimizer/explainability/__init__.py
meta_optimizer/explainability/explainer_factory.py
meta_optimizer/meta/__init__.py
meta_optimizer/meta/meta_optimizer.py
meta_optimizer/meta/optimization_history.py
meta_optimizer/meta/problem_analysis.py
meta_optimizer/meta/selection_tracker.py
meta_optimizer/optimizers/__init__.py
meta_optimizer/optimizers/aco.py
meta_optimizer/optimizers/base_optimizer.py
meta_optimizer/optimizers/de.py
meta_optimizer/optimizers/es.py
meta_optimizer/optimizers/gwo.py
meta_optimizer/optimizers/optimizer_factory.py
meta_optimizer/utils/__init__.py
meta_optimizer/utils/plot_utils.py
meta_optimizer/visualization/__init__.py
meta_optimizer/visualization/drift_analysis.py
meta_optimizer/visualization/live_visualization.py
meta_optimizer/visualization/optimizer_analysis.py
meta_optimizer_mdt_test-0.1.1.dist-info/LICENSE
meta_optimizer_mdt_test-0.1.1.dist-info/METADATA
meta_optimizer_mdt_test-0.1.1.dist-info/WHEEL
meta_optimizer_mdt_test-0.1.1.dist-info/entry_points.txt
meta_optimizer_mdt_test-0.1.1.dist-info/top_level.txt
meta_optimizer_mdt_test-0.1.1.dist-info/RECORD
