Metadata-Version: 2.2
Name: meta_optimizer_mdt_test
Version: 0.1.1
Summary: Meta-Optimizer Framework for optimization, meta-learning, explainability, and drift detection
Home-page: https://github.com/example/meta_optimizer
Author: MDT Team
Author-email: MDT Team <Blair.Dupre@und.edu>
License: MIT License
Project-URL: Homepage, https://github.com/bddupre92/mdt_Test/tree/optimization-feature
Project-URL: Issues, https://github.com/bddupre92/mdt_Test/issues
Project-URL: Documentation, https://bddupre92.github.io/mdt_Test/#examples
Keywords: optimization,meta-learning,explainability,drift-detection,hyperparameter-tuning
Classifier: Development Status :: 3 - Alpha
Classifier: Intended Audience :: Science/Research
Classifier: Programming Language :: Python :: 3
Classifier: Programming Language :: Python :: 3.8
Classifier: Programming Language :: Python :: 3.9
Classifier: Programming Language :: Python :: 3.10
Classifier: License :: OSI Approved :: MIT License
Classifier: Topic :: Scientific/Engineering :: Artificial Intelligence
Classifier: Topic :: Scientific/Engineering :: Mathematics
Requires-Python: >=3.8
License-File: LICENSE
Requires-Dist: numpy>=1.19.0
Requires-Dist: pandas>=1.3.0
Requires-Dist: scikit-learn>=1.0.0
Requires-Dist: matplotlib>=3.4.0
Requires-Dist: seaborn>=0.11.0
Requires-Dist: scipy>=1.7.0
Requires-Dist: joblib>=1.1.0
Requires-Dist: tqdm>=4.60.0
Requires-Dist: plotly>=5.5.0
Requires-Dist: torch>=2.0.0
Provides-Extra: explainability
Requires-Dist: shap>=0.40.0; extra == "explainability"
Requires-Dist: lime>=0.2.0; extra == "explainability"
Requires-Dist: eli5>=0.11.0; extra == "explainability"
Requires-Dist: interpret>=0.2.7; extra == "explainability"
Provides-Extra: optimization
Requires-Dist: deap>=1.3.1; extra == "optimization"
Requires-Dist: hyperopt>=0.2.7; extra == "optimization"
Requires-Dist: optuna>=3.0.0; extra == "optimization"
Provides-Extra: dev
Requires-Dist: pytest>=7.0.0; extra == "dev"
Requires-Dist: pytest-cov>=4.0.0; extra == "dev"
Requires-Dist: black>=22.0.0; extra == "dev"
Requires-Dist: flake8>=5.0.0; extra == "dev"
Dynamic: author
Dynamic: home-page
Dynamic: requires-python
